dist
paceENSDF
tests
