Metadata-Version: 2.1
Name: paceENSDF
Version: 0.5.0
Summary: paceENSDF: Python Archive of Coincident Emissions from ENSDF.  Package enables interaction, manipulation, analysis, and visualization of radioactive-decay data from the ENSDF archive and corresponding coincidence gamma-gamma and gamma-X-ray emissions.
Home-page: https://github.com/AaronMHurst/pace_ensdf
Author: Aaron M. Hurst
Author-email: amhurst@berkeley.edu
Classifier: Development Status :: 4 - Beta
Classifier: Intended Audience :: Science/Research
Classifier: License :: OSI Approved :: BSD License
Classifier: Operating System :: MacOS
Classifier: Operating System :: Unix
Classifier: Programming Language :: Python
Classifier: Programming Language :: Python :: 3
Classifier: Programming Language :: Python :: 3.7
Classifier: Topic :: Scientific/Engineering :: Physics
Requires-Dist: numpy
Requires-Dist: pandas
Requires-Dist: pytest
